ami_nedm
setup.py
pyAMI_nedm/__init__.py
pyAMI_nedm/config.py
pyAMI_nedm/exception.py
pyAMI_nedm/parsers.py
pyAMI_nedm/run.py
pyAMI_nedm/run_finder.py
pyAMI_nedm/updater.py
pyAMI_nedm.egg-info/PKG-INFO
pyAMI_nedm.egg-info/SOURCES.txt
pyAMI_nedm.egg-info/dependency_links.txt
pyAMI_nedm.egg-info/not-zip-safe
pyAMI_nedm.egg-info/requires.txt
pyAMI_nedm.egg-info/top_level.txt