Metadata-Version: 1.0
Name: pyAMI-nedm
Version: 5.0.2
Summary: Python ATLAS Metadata Interface (pyAMI) for nEDM
Home-page: http://ami.in2p3.fr/
Author: Jerome Odier
Author-email: jerome.odier@cern.ch
License: CeCILL-C
Platform: any
